[
  {
    "id": 0,
    "name": "Muhammad Albagir",
    "title": "World Class",
    "thumbnail_img": "https://d10dnch8g6iuzs.cloudfront.net/picture/20420170807150752758_o",
    "field_img": "https://lapanganfutsal.id/wp-content/uploads/2017/09/jenis-lapangan-futsal-parquette-1024x682.jpg",
    "field_name": "Cipedes Futsal Arena",
    "field_date": "Jum'at 2 Maret",
    "field_type": "Parquette",
    "field_num": "Lap. 3",
    "schedule": "19.00 - 20.00",
    "created_at": "3m",
    "updated_at": "3m"
  },
  {
    "id": 1,
    "name":"Muhammad Yusuf Kurniawan",
    "title":"World Class",
    "thumbnail_img":"https://d10dnch8g6iuzs.cloudfront.net/picture/73820170807150839262_o",
    "field_img":"https://www.forekicks.com/taunton/Shared/images/fields1.jpg",
    "field_name":"YPKP Futsal Arena",
    "field_date":"Sabtu 3 Maret",
    "field_type":"Synthetic",
    "field_num": "Lap. 7",
    "schedule":"16.00 - 17.00",
    "created_at": "1h",
    "updated_at": "1h"
  },
  {
    "id": 2,
    "name":"Tricahyo Ramadhan",
    "title":"Professional",
    "thumbnail_img":"https://d10dnch8g6iuzs.cloudfront.net/picture/37220170807153201515_o",
    "field_img":"http://image.made-in-china.com/2f0j00zviEmVDsCBUW/Porous-Futsal-Pitch-Interlocking-Flooring-Dranage-Futsal-Tiles-International-Standard.jpg",
    "field_name":"Planet Futsal",
    "field_date":"Minggu 4 Maret",
    "field_type":"Vinyl",
    "field_num": "Lap. 5",
    "schedule":"15.00 - 17.00",
    "created_at": "4h",
    "updated_at": "4h"
  },
  {
    "id": 3,
    "name":"Andriansyah Agustin",
    "title":"Semi Pro",
    "thumbnail_img":"https://d10dnch8g6iuzs.cloudfront.net/picture/21420170807153210854_o",
    "field_img":"https://www.forekicks.com/taunton/Shared/images/fields1.jpg",
    "field_name":"YPKP Futsal Arena",
    "field_date":"Minggu 4 Maret",
    "field_type":"Synthetic",
    "field_num": "Lap. 7",
    "schedule":"15.00 - 16.00",
    "created_at": "4h",
    "updated_at": "4h"
  },
  {
    "id": 4,
    "name":"Rio Pangestu Putra",
    "title":"Professional",
    "thumbnail_img":"https://d10dnch8g6iuzs.cloudfront.net/picture/85120170807153242648_o",
    "field_img":"https://s.kaskus.id/images/fjb/2015/03/06/lapangan_futsal_di_semarang_1565249_1425611821.jpg",
    "field_name":"YPKP Futsal Arena",
    "field_date":"Kamis 8 Maret",
    "field_type":"Cement",
    "field_num": "Lap. 1",
    "schedule":"19.00 - 20.00",
    "created_at": "1d",
    "updated_at": "1d"
  }
]
